lib/main.py
huddu_cli-1.0.0.dist-info/METADATA
huddu_cli-1.0.0.dist-info/WHEEL
huddu_cli-1.0.0.dist-info/top_level.txt
huddu_cli-1.0.0.dist-info/RECORD
