Metadata-Version: 2.1
Name: huddu-cli
Version: 1.0.0
Summary: Official CLI for huddu.io
Home-page: https://github.com/hudduapp/cli
Author: Joshua3212
Author-email: hello@huddu.io
License: MIT
Requires: typer
Requires: rich
Requires: huddu
